README.rst
setup.py
python_socketio_client.egg-info/PKG-INFO
python_socketio_client.egg-info/SOURCES.txt
python_socketio_client.egg-info/dependency_links.txt
python_socketio_client.egg-info/not-zip-safe
python_socketio_client.egg-info/requires.txt
python_socketio_client.egg-info/top_level.txt
socketio_client/__init__.py
socketio_client/manager.py
socketio_client/parser.py
socketio_client/socket.py