Metadata-Version: 1.1
Name: python-socketio-client
Version: 0.1
Summary: Socket.IO client
Home-page: https://github.com/Utkarsh-vishnoi/python-engineio-client/archive/1.0.tar.gz
Author: Frédéric Sureau
Author-email: frederic.sureau@veo-labs.com
License: MIT
Platform: any
Classifier: Environment :: Web Environment
Classifier: Intended Audience :: Developers
Classifier: License :: OSI Approved :: MIT License
Classifier: Operating System :: OS Independent
Classifier: Programming Language :: Python
Classifier: Programming Language :: Python :: 2
Classifier: Programming Language :: Python :: 3
Classifier: Topic :: Internet :: WWW/HTTP :: Dynamic Content
Classifier: Topic :: Software Development :: Libraries :: Python Modules
